{"data":[{"NCS":"9W2OGK","Nickname":"Man Pangkor","QTH":"Setiawan, Perak","LOCATOR":"OJ04HE","Name":"KAMARUDZAMAN BIN ABDUL RAHIM ","G":"👨🏻‍💻","CAT":"HAM-MS","CT":"6","MAX":"65","AVG":"43","KPI":"65.9%","R":"01"},{"NCS":"9W2UZL","Nickname":"Ust. Zul","QTH":"Bukit Beruntung, Selangor","LOCATOR":"OJ03SK","Name":"ZULKIFLI BIN ABU ","G":"👨🏻","CAT":"HAM-MS","CT":"3","MAX":"63","AVG":"49","KPI":"74.9%","R":"02"},{"NCS":"9M2SFL","Nickname":"Saiful","QTH":"Simpang Renggam, Johor","LOCATOR":"OJ11QU","Name":"SAIFUL AZHAR BIN ABDULLAH ","G":"👨🏻","CAT":"HAM-MS","CT":"14","MAX":"63","AVG":"47","KPI":"72.3%","R":"03"},{"NCS":"9M2RAN","Nickname":"Imran","QTH":"Kepala Batas, Kedah","LOCATOR":"OJ06EF","Name":"NOR IMRAN BIN AZIZ ","G":"👴🏻","CAT":"HAM-MS","CT":"1","MAX":"61","AVG":"61","KPI":"93.8%","R":"04"},{"NCS":"9W2YJT","Nickname":"Yusof","QTH":"Pendang, Kedah","LOCATOR":"OJ05HX","Name":"MOHAMAD YUSOF BIN SAFAR ","G":"👨🏻","CAT":"HAM-MS","CT":"3","MAX":"61","AVG":"45","KPI":"68.7%","R":"05"},{"NCS":"9W2AYP","Nickname":"Sabri","QTH":"Mentakab, Pahang","LOCATOR":"OJ13DL","Name":"MOHD SABRI BIN IBRAHIM ","G":"👨🏻","CAT":"HAM-MS","CT":"7","MAX":"58","AVG":"47","KPI":"72.3%","R":"06"},{"NCS":"9W6MOZ","Nickname":"Mus","QTH":"Papar, Sabah","LOCATOR":"OJ75XR","Name":"MUSTAFA BIN OMAR ","G":"👨🏻","CAT":"HAM-MS","CT":"8","MAX":"58","AVG":"36","KPI":"54.8%","R":"07"},{"NCS":"9M6RMD","Nickname":"Rosni","QTH":"WP Labuan","LOCATOR":"OJ75OI","Name":"ROSNI BIN MOHD DAUD ","G":"👨🏻","CAT":"HAM-MS","CT":"6","MAX":"57","AVG":"43","KPI":"66.4%","R":"08"},{"NCS":"9W2YBT","Nickname":"Faisal","QTH":"Chanis, Muadzam, Pahang","LOCATOR":"OJ12LU","Name":"MOHD FAISAL BIN MOHD ZIN ","G":"👨🏻","CAT":"HAM-MS","CT":"5","MAX":"57","AVG":"38","KPI":"59.1%","R":"09"},{"NCS":"9W2YHM","Nickname":"Helmi","QTH":"Ipoh, Perak","LOCATOR":"OJ04MN","Name":"MOHD HELMI BIN ABDULLAH ","G":"👨🏻","CAT":"HAM-MS","CT":"9","MAX":"53","AVG":"27","KPI":"42.2%","R":"10"},{"NCS":"V85AFF","Nickname":"Mahathir","QTH":"Tnh. Jambu, Brunei","LOCATOR":"OJ75MA","Name":"MAHATHIR ARIFFIN ","G":"👨🏻","CAT":"HAM-MS","CT":"7","MAX":"52","AVG":"36","KPI":"54.9%","R":"11"},{"NCS":"9M6JAY","Nickname":"John Junior","QTH":"Kota Kinabalu, Sabah","LOCATOR":"OJ85BW","Name":"JOHN JOSHUA JUNIOR ","G":"👨🏻","CAT":"HAM-MS","CT":"5","MAX":"51","AVG":"44","KPI":"67.7%","R":"12"},{"NCS":"9W6RHN","Nickname":"Roslan","QTH":"Kota Kinabalu, Sabah","LOCATOR":"OJ85BX","Name":"ROSLAN BIN A. NUNSI ","G":"👨🏻","CAT":"HAM-MS","CT":"4","MAX":"48","AVG":"39","KPI":"60.4%","R":"13"},{"NCS":"9W2LGX","Nickname":"Fizi","QTH":"Puncak Alam, K. Selangor","LOCATOR":"OJ03RF","Name":"MOHAMAD HAFIZI BIN RUSLAN ","G":"👨🏻","CAT":"HAM-MS","CT":"2","MAX":"47","AVG":"41","KPI":"63.1%","R":"14"},{"NCS":"9W2ESR","Nickname":"Maman","QTH":"Batu Ferringgi, Penang","LOCATOR":"OJ05CL","Name":"MOHAMMAD SULAIMAN BIN ESA ","G":"👨🏻","CAT":"HAM-MS","CT":"2","MAX":"46","AVG":"46","KPI":"70.0%","R":"15"},{"NCS":"9M6RDY","Nickname":"Rudy","QTH":"Papar, Sabah","LOCATOR":"OJ85BX","Name":"MATTHEUS @ RUDY BIN BENEDICT ","G":"👨🏻","CAT":"HAM-MS","CT":"2","MAX":"46","AVG":"37","KPI":"56.9%","R":"16"},{"NCS":"9W6AZE","Nickname":"Hazari","QTH":"Senai, Johor","LOCATOR":"OJ11TO","Name":"HAZARI BIN MOHAMED GHANI ","G":"👨🏻","CAT":"HAM-MS","CT":"6","MAX":"46","AVG":"34","KPI":"52.3%","R":"17"},{"NCS":"9W6WOT","Nickname":"Steward","QTH":"Papar, Sabah","LOCATOR":"OJ75XR","Name":"STEWARD DESOUZA STANISLAUS ","G":"👨🏻","CAT":"HAM-MS","CT":"2","MAX":"38","AVG":"34","KPI":"52.3%","R":"18"},{"NCS":"9W2SNN","Nickname":"Samsul","QTH":"Tampoi, Johor Bahru","LOCATOR":"OJ11UM","Name":"SAMSUL BAHARI BIN RAHMAT ","G":"👨🏻","CAT":"HAM-MS","CT":"4","MAX":"38","AVG":"23","KPI":"35.4%","R":"19"},{"NCS":"9M6AUA","Nickname":"Jeofrey","QTH":"Papar, Sabah","LOCATOR":"OJ85AW","Name":"JEOFREY BIN AVITUS @ VITUS ","G":"👨🏻‍🎓","CAT":"HAM-MS","CT":"1","MAX":"34","AVG":"34","KPI":"52.3%","R":"20"},{"NCS":"9W2NDI","Nickname":"Nasaruddin","QTH":"Sg. Baru Trong, Perak","LOCATOR":"OJ04IO","Name":"NASARUDDIN BIN ARIF ","G":"👨🏻","CAT":"HAM-MS","CT":"3","MAX":"31","AVG":"23","KPI":"35.9%","R":"21"},{"NCS":"9W2JCP","Nickname":"Rosli","QTH":"Skudai, Johor Bahru","LOCATOR":"OJ11TN","Name":"MOHAMAD ROSLI BIN AWANG ","G":"👨🏻","CAT":"HAM-MS","CT":"1","MAX":"26","AVG":"26","KPI":"40.0%","R":"22"},{"NCS":"9W6PKJ","Nickname":"Janson @ Iskandar","QTH":"Tuaran, Sabah","LOCATOR":"OJ85FB","Name":"JANSON BIN JUWILY @ JACK PAHIRA ","G":"👨🏻","CAT":"HAM-MS","CT":"2","MAX":"24","AVG":"21","KPI":"32.3%","R":"23"},{"NCS":"9W8VYY","Nickname":"Alex","QTH":"Kuching, Sarawak","LOCATOR":"OJ51EM","Name":"VOON YEAN YEE ","G":"👨🏻","CAT":"HAM-MS","CT":"2","MAX":"24","AVG":"10","KPI":"14.6%","R":"24"},{"NCS":"9W2EZK","Nickname":"Zikry","QTH":"Kuang, Sg. Buloh, Selangor","LOCATOR":"OJ03SF","Name":"MOHD IFFIQ ZIKRY BIN JAMAL ","G":"👨🏻","CAT":"HAM-MS","CT":"2","MAX":"23","AVG":"23","KPI":"34.6%","R":"25"},{"NCS":"9M6RHM","Nickname":"Rahim","QTH":"Kota Kinabalu, Sabah","LOCATOR":"OJ85AV","Name":"ABDUL RAHIM BIN MARJAYA ","G":"👨🏻","CAT":"HAM-MS","CT":"1","MAX":"0","AVG":"0","KPI":"0.0%","R":"26"}]}